AnsiColorPrinter.py
__init__.py
AnsiColorPrinter-0.0.2.dist-info/METADATA
AnsiColorPrinter-0.0.2.dist-info/WHEEL
AnsiColorPrinter-0.0.2.dist-info/top_level.txt
AnsiColorPrinter-0.0.2.dist-info/RECORD
